datamana/__init__.py
datamana/torch.py
datamana-0.0.1.dist-info/LICENSE
datamana-0.0.1.dist-info/METADATA
datamana-0.0.1.dist-info/WHEEL
datamana-0.0.1.dist-info/top_level.txt
datamana-0.0.1.dist-info/RECORD
