Metadata-Version: 2.1
Name: datamana
Version: 0.0.1
Summary: Dataset Manager
Home-page: https://github.com/JiauZhang/datamana
Author: JiauZhang
Author-email: jiauzhang@163.com
License: MIT
Keywords: Deep Learning,Dataset Manager,Artificial Intelligence
Classifier: Intended Audience :: Developers
Classifier: Topic :: Scientific/Engineering :: Artificial Intelligence
Classifier: License :: OSI Approved :: MIT License
Classifier: Programming Language :: Python :: 3.8
License-File: LICENSE
Requires-Dist: numpy
